monopoly_simulator/__init__.py
monopoly_simulator/action_choices.py
monopoly_simulator/agent.py
monopoly_simulator/agent_helper_functions.py
monopoly_simulator/agent_helper_functions_v2.py
monopoly_simulator/agent_helper_functions_v3.py
monopoly_simulator/background_agent_v1_2.py
monopoly_simulator/background_agent_v3_1.py
monopoly_simulator/background_agent_v3_1_action_novelty.py
monopoly_simulator/background_agent_v3_1_cash_conservator.py
monopoly_simulator/background_agent_v3_1_interaction_accept_offer.py
monopoly_simulator/background_agent_v3_1_interaction_make_offer.py
monopoly_simulator/background_agent_v3_1_railroad_chaser.py
monopoly_simulator/background_agent_v3_1_sneaky_trader.py
monopoly_simulator/background_agent_v3_2.py
monopoly_simulator/background_agent_v4_1.py
monopoly_simulator/background_agent_v4_1_avoid_accept_trade_with_others.py
monopoly_simulator/background_agent_v4_1_avoid_accept_trade_with_ta2.py
monopoly_simulator/background_agent_v4_1_avoid_accept_trade_with_wealthy.py
monopoly_simulator/background_agent_v5_1.py
monopoly_simulator/bank.py
monopoly_simulator/card.py
monopoly_simulator/card_utility_actions.py
monopoly_simulator/client_agent.py
monopoly_simulator/client_agent_serial.py
monopoly_simulator/diagnostics.py
monopoly_simulator/dice.py
monopoly_simulator/execute_phase3.py
monopoly_simulator/flag_config.py
monopoly_simulator/gameplay.py
monopoly_simulator/gameplay_GUI.py
monopoly_simulator/gameplay_socket.py
monopoly_simulator/gameplay_socket_phase3.py
monopoly_simulator/gameplay_socket_ta2.py
monopoly_simulator/initialize_game_elements.py
monopoly_simulator/location.py
monopoly_simulator/log_metrics.py
monopoly_simulator/logging_info.py
monopoly_simulator/monopoly_game_schema_v1-2.json
monopoly_simulator/novelty_distributions_v2.py
monopoly_simulator/novelty_distributions_v3.py
monopoly_simulator/novelty_functions.py
monopoly_simulator/novelty_functions_v2.py
monopoly_simulator/novelty_functions_v3.py
monopoly_simulator_test-0.0.9.dist-info/LICENSE
monopoly_simulator_test-0.0.9.dist-info/METADATA
monopoly_simulator_test-0.0.9.dist-info/WHEEL
monopoly_simulator_test-0.0.9.dist-info/top_level.txt
monopoly_simulator_test-0.0.9.dist-info/RECORD
