Metadata-Version: 2.1
Name: monopoly-simulator-test
Version: 0.0.9
Summary: USC/ISI monopoly simulator
Home-page: https://github.com/mayankkejriwal/GNOME-p3/tree/phase3_simulator_v1
Author: Min-Hsueh Chiu
Author-email: minhsueh@isi.edu
License: UNKNOWN
Platform: UNKNOWN
Requires-Python: ==3.7.6
License-File: LICENSE
Requires-Dist: numpy (==1.18.4)
Requires-Dist: xlsxwriter (==1.2.8)
